supermemory/__init__.py
supermemory/_base_client.py
supermemory/_client.py
supermemory/_compat.py
supermemory/_constants.py
supermemory/_exceptions.py
supermemory/_files.py
supermemory/_models.py
supermemory/_qs.py
supermemory/_resource.py
supermemory/_response.py
supermemory/_streaming.py
supermemory/_types.py
supermemory/_version.py
supermemory/py.typed
supermemory/_utils/__init__.py
supermemory/_utils/_compat.py
supermemory/_utils/_datetime_parse.py
supermemory/_utils/_json.py
supermemory/_utils/_logs.py
supermemory/_utils/_proxy.py
supermemory/_utils/_reflection.py
supermemory/_utils/_resources_proxy.py
supermemory/_utils/_streams.py
supermemory/_utils/_sync.py
supermemory/_utils/_transform.py
supermemory/_utils/_typing.py
supermemory/_utils/_utils.py
supermemory/lib/.keep
supermemory/resources/__init__.py
supermemory/resources/connections.py
supermemory/resources/documents.py
supermemory/resources/memories.py
supermemory/resources/search.py
supermemory/resources/settings.py
supermemory/types/__init__.py
supermemory/types/add_response.py
supermemory/types/client_add_params.py
supermemory/types/client_profile_params.py
supermemory/types/connection_configure_params.py
supermemory/types/connection_configure_response.py
supermemory/types/connection_create_params.py
supermemory/types/connection_create_response.py
supermemory/types/connection_delete_by_id_response.py
supermemory/types/connection_delete_by_provider_params.py
supermemory/types/connection_delete_by_provider_response.py
supermemory/types/connection_get_by_id_response.py
supermemory/types/connection_get_by_tag_params.py
supermemory/types/connection_get_by_tag_response.py
supermemory/types/connection_import_params.py
supermemory/types/connection_import_response.py
supermemory/types/connection_list_documents_params.py
supermemory/types/connection_list_documents_response.py
supermemory/types/connection_list_params.py
supermemory/types/connection_list_response.py
supermemory-3.21.0.dist-info/METADATA
supermemory-3.21.0.dist-info/WHEEL
supermemory-3.21.0.dist-info/licenses/LICENSE
supermemory-3.21.0.dist-info/RECORD
